Workbook

Sheet Read me
A1: Taskiem QA tracker: 2 to 27 November 2026
A2: ISPEND DIGITAL SERVICES LTD · Confidential · Goes with the QA test plan
A4: How to use it
A5: Fill in | B5: Only the shaded (light green-grey) columns. Everything else is filled in already or counts itself.
A6: Test cases | B6: One row per case, already in the order of the plan, with its planned day. Filter by Day to see today's cases. Fill in Result, Date run, Device and browser, Bug IDs and Notes.
A7: Bugs | B7: One row per bug. Row 4 is an example: copy its style, then delete it before your first weekly report. IDs go BUG-001, BUG-002… and are never reused.
A8: Daily log | B8: One row per day, already dated. The case counts fill themselves from the Test cases tab; you fill in the rest by 17:30.
A9: Exploratory | B9: The five planned sessions with their charters. Fill in what you did and found.
A10: Accounts | B10: Your test identities and organisations. Never write a password here.
A11: Summary | B11: Counts that fill themselves: results by area and by day, bugs by severity and status, and the KPIs. Copy these into your weekly report.
A13: Result words | B13: Pass · Pass with note · Fail · Blocked · Not run (choose from the list in the cell)
A14: Severity | B14: S1 Critical: money, data or trust at risk; message the engineering lead within 1 hour · S2 Major: a feature does not work, no way round · S3 Minor: works badly or with a way round · S4 Small: wording, looks, suggestions
A15: Bug status | B15: New · Confirmed · Needs info · In progress · Fixed: ready to retest · Closed · Reopened · Won't fix · Duplicate · Not a bug
A16: R | B16: R in the Regression column marks the 66 cases run before every release.
A17: Rules | B17: Test data only. Never a real customer's details, a real card number or a live payment key. Never a password in this file.

Sheet Summary
A1: Summary
A2: Fills itself from the other tabs. Copy into the weekly report.
A4: Results by area | B4: Cases | C4: Pass | D4: Pass with note | E4: Fail | F4: Blocked | G4: Not run | H4: No result yet | I4: % with a result
A5: Smoke test | B5: =COUNTIF('Test cases'!$B$2:$B$380,A5) -> 8 | C5: =COUNTIFS('Test cases'!$B$2:$B$380,$A5,'Test cases'!$J$2:$J$380,"Pass") -> 0 | D5: =COUNTIFS('Test cases'!$B$2:$B$380,$A5,'Test cases'!$J$2:$J$380,"Pass with note") -> 0 | E5: =COUNTIFS('Test cases'!$B$2:$B$380,$A5,'Test cases'!$J$2:$J$380,"Fail") -> 0 | F5: =COUNTIFS('Test cases'!$B$2:$B$380,$A5,'Test cases'!$J$2:$J$380,"Blocked") -> 0 | G5: =COUNTIFS('Test cases'!$B$2:$B$380,$A5,'Test cases'!$J$2:$J$380,"Not run") -> 0 | H5: =B5-SUM(C5:G5) -> 8 | I5: =IF(B5=0,0,SUM(C5:F5)/B5) -> 0
A6: Core platform | B6: =COUNTIF('Test cases'!$B$2:$B$380,A6) -> 70 | C6: =COUNTIFS('Test cases'!$B$2:$B$380,$A6,'Test cases'!$J$2:$J$380,"Pass") -> 0 | D6: =COUNTIFS('Test cases'!$B$2:$B$380,$A6,'Test cases'!$J$2:$J$380,"Pass with note") -> 0 | E6: =COUNTIFS('Test cases'!$B$2:$B$380,$A6,'Test cases'!$J$2:$J$380,"Fail") -> 0 | F6: =COUNTIFS('Test cases'!$B$2:$B$380,$A6,'Test cases'!$J$2:$J$380,"Blocked") -> 0 | G6: =COUNTIFS('Test cases'!$B$2:$B$380,$A6,'Test cases'!$J$2:$J$380,"Not run") -> 0 | H6: =B6-SUM(C6:G6) -> 70 | I6: =IF(B6=0,0,SUM(C6:F6)/B6) -> 0
A7: Chat (Telegram) | B7: =COUNTIF('Test cases'!$B$2:$B$380,A7) -> 20 | C7: =COUNTIFS('Test cases'!$B$2:$B$380,$A7,'Test cases'!$J$2:$J$380,"Pass") -> 0 | D7: =COUNTIFS('Test cases'!$B$2:$B$380,$A7,'Test cases'!$J$2:$J$380,"Pass with note") -> 0 | E7: =COUNTIFS('Test cases'!$B$2:$B$380,$A7,'Test cases'!$J$2:$J$380,"Fail") -> 0 | F7: =COUNTIFS('Test cases'!$B$2:$B$380,$A7,'Test cases'!$J$2:$J$380,"Blocked") -> 0 | G7: =COUNTIFS('Test cases'!$B$2:$B$380,$A7,'Test cases'!$J$2:$J$380,"Not run") -> 0 | H7: =B7-SUM(C7:G7) -> 20 | I7: =IF(B7=0,0,SUM(C7:F7)/B7) -> 0
A8: Reconciliation: invoices, payments and money | B8: =COUNTIF('Test cases'!$B$2:$B$380,A8) -> 95 | C8: =COUNTIFS('Test cases'!$B$2:$B$380,$A8,'Test cases'!$J$2:$J$380,"Pass") -> 0 | D8: =COUNTIFS('Test cases'!$B$2:$B$380,$A8,'Test cases'!$J$2:$J$380,"Pass with note") -> 0 | E8: =COUNTIFS('Test cases'!$B$2:$B$380,$A8,'Test cases'!$J$2:$J$380,"Fail") -> 0 | F8: =COUNTIFS('Test cases'!$B$2:$B$380,$A8,'Test cases'!$J$2:$J$380,"Blocked") -> 0 | G8: =COUNTIFS('Test cases'!$B$2:$B$380,$A8,'Test cases'!$J$2:$J$380,"Not run") -> 0 | H8: =B8-SUM(C8:G8) -> 95 | I8: =IF(B8=0,0,SUM(C8:F8)/B8) -> 0
A9: Storefronts, orders, bookings, forms and agents | B9: =COUNTIF('Test cases'!$B$2:$B$380,A9) -> 76 | C9: =COUNTIFS('Test cases'!$B$2:$B$380,$A9,'Test cases'!$J$2:$J$380,"Pass") -> 0 | D9: =COUNTIFS('Test cases'!$B$2:$B$380,$A9,'Test cases'!$J$2:$J$380,"Pass with note") -> 0 | E9: =COUNTIFS('Test cases'!$B$2:$B$380,$A9,'Test cases'!$J$2:$J$380,"Fail") -> 0 | F9: =COUNTIFS('Test cases'!$B$2:$B$380,$A9,'Test cases'!$J$2:$J$380,"Blocked") -> 0 | G9: =COUNTIFS('Test cases'!$B$2:$B$380,$A9,'Test cases'!$J$2:$J$380,"Not run") -> 0 | H9: =B9-SUM(C9:G9) -> 76 | I9: =IF(B9=0,0,SUM(C9:F9)/B9) -> 0
A10: Schools | B10: =COUNTIF('Test cases'!$B$2:$B$380,A10) -> 96 | C10: =COUNTIFS('Test cases'!$B$2:$B$380,$A10,'Test cases'!$J$2:$J$380,"Pass") -> 0 | D10: =COUNTIFS('Test cases'!$B$2:$B$380,$A10,'Test cases'!$J$2:$J$380,"Pass with note") -> 0 | E10: =COUNTIFS('Test cases'!$B$2:$B$380,$A10,'Test cases'!$J$2:$J$380,"Fail") -> 0 | F10: =COUNTIFS('Test cases'!$B$2:$B$380,$A10,'Test cases'!$J$2:$J$380,"Blocked") -> 0 | G10: =COUNTIFS('Test cases'!$B$2:$B$380,$A10,'Test cases'!$J$2:$J$380,"Not run") -> 0 | H10: =B10-SUM(C10:G10) -> 96 | I10: =IF(B10=0,0,SUM(C10:F10)/B10) -> 0
A11: Across the product | B11: =COUNTIF('Test cases'!$B$2:$B$380,A11) -> 14 | C11: =COUNTIFS('Test cases'!$B$2:$B$380,$A11,'Test cases'!$J$2:$J$380,"Pass") -> 0 | D11: =COUNTIFS('Test cases'!$B$2:$B$380,$A11,'Test cases'!$J$2:$J$380,"Pass with note") -> 0 | E11: =COUNTIFS('Test cases'!$B$2:$B$380,$A11,'Test cases'!$J$2:$J$380,"Fail") -> 0 | F11: =COUNTIFS('Test cases'!$B$2:$B$380,$A11,'Test cases'!$J$2:$J$380,"Blocked") -> 0 | G11: =COUNTIFS('Test cases'!$B$2:$B$380,$A11,'Test cases'!$J$2:$J$380,"Not run") -> 0 | H11: =B11-SUM(C11:G11) -> 14 | I11: =IF(B11=0,0,SUM(C11:F11)/B11) -> 0
A12: All | B12: =SUM(B5:B11) -> 379 | C12: =SUM(C5:C11) -> 0 | D12: =SUM(D5:D11) -> 0 | E12: =SUM(E5:E11) -> 0 | F12: =SUM(F5:F11) -> 0 | G12: =SUM(G5:G11) -> 0 | H12: =SUM(H5:H11) -> 379 | I12: =IF(B12=0,0,SUM(C12:F12)/B12) -> 0
A15: Bugs by severity | B15: Logged | C15: Open | D15: Fixed: ready to retest | E15: Closed | F15: Reopened | G15: Won't fix, duplicate, not a bug | H15: Needs info
A16: S1 | B16: =COUNTIF(Bugs!$J$5:$J$303,A16) -> 0 | C16: =B16-E16-G16 -> 0 | D16: =COUNTIFS(Bugs!$J$5:$J$303,A16,Bugs!$O$5:$O$303,"Fixed: ready to retest") -> 0 | E16: =COUNTIFS(Bugs!$J$5:$J$303,A16,Bugs!$O$5:$O$303,"Closed") -> 0 | F16: =COUNTIFS(Bugs!$J$5:$J$303,A16,Bugs!$O$5:$O$303,"Reopened") -> 0 | G16: =COUNTIFS(Bugs!$J$5:$J$303,A16,Bugs!$O$5:$O$303,"Won't fix")+COUNTIFS(Bugs!$J$5:$J$303,A16,Bugs!$O$5:$O$303,"Duplicate")+COUNTIFS(Bugs!$J$5:$J$303,A16,Bugs!$O$5:$O$303,"Not a bug") -> 0 | H16: =COUNTIFS(Bugs!$J$5:$J$303,A16,Bugs!$O$5:$O$303,"Needs info") -> 0
A17: S2 | B17: =COUNTIF(Bugs!$J$5:$J$303,A17) -> 0 | C17: =B17-E17-G17 -> 0 | D17: =COUNTIFS(Bugs!$J$5:$J$303,A17,Bugs!$O$5:$O$303,"Fixed: ready to retest") -> 0 | E17: =COUNTIFS(Bugs!$J$5:$J$303,A17,Bugs!$O$5:$O$303,"Closed") -> 0 | F17: =COUNTIFS(Bugs!$J$5:$J$303,A17,Bugs!$O$5:$O$303,"Reopened") -> 0 | G17: =COUNTIFS(Bugs!$J$5:$J$303,A17,Bugs!$O$5:$O$303,"Won't fix")+COUNTIFS(Bugs!$J$5:$J$303,A17,Bugs!$O$5:$O$303,"Duplicate")+COUNTIFS(Bugs!$J$5:$J$303,A17,Bugs!$O$5:$O$303,"Not a bug") -> 0 | H17: =COUNTIFS(Bugs!$J$5:$J$303,A17,Bugs!$O$5:$O$303,"Needs info") -> 0
A18: S3 | B18: =COUNTIF(Bugs!$J$5:$J$303,A18) -> 0 | C18: =B18-E18-G18 -> 0 | D18: =COUNTIFS(Bugs!$J$5:$J$303,A18,Bugs!$O$5:$O$303,"Fixed: ready to retest") -> 0 | E18: =COUNTIFS(Bugs!$J$5:$J$303,A18,Bugs!$O$5:$O$303,"Closed") -> 0 | F18: =COUNTIFS(Bugs!$J$5:$J$303,A18,Bugs!$O$5:$O$303,"Reopened") -> 0 | G18: =COUNTIFS(Bugs!$J$5:$J$303,A18,Bugs!$O$5:$O$303,"Won't fix")+COUNTIFS(Bugs!$J$5:$J$303,A18,Bugs!$O$5:$O$303,"Duplicate")+COUNTIFS(Bugs!$J$5:$J$303,A18,Bugs!$O$5:$O$303,"Not a bug") -> 0 | H18: =COUNTIFS(Bugs!$J$5:$J$303,A18,Bugs!$O$5:$O$303,"Needs info") -> 0
A19: S4 | B19: =COUNTIF(Bugs!$J$5:$J$303,A19) -> 0 | C19: =B19-E19-G19 -> 0 | D19: =COUNTIFS(Bugs!$J$5:$J$303,A19,Bugs!$O$5:$O$303,"Fixed: ready to retest") -> 0 | E19: =COUNTIFS(Bugs!$J$5:$J$303,A19,Bugs!$O$5:$O$303,"Closed") -> 0 | F19: =COUNTIFS(Bugs!$J$5:$J$303,A19,Bugs!$O$5:$O$303,"Reopened") -> 0 | G19: =COUNTIFS(Bugs!$J$5:$J$303,A19,Bugs!$O$5:$O$303,"Won't fix")+COUNTIFS(Bugs!$J$5:$J$303,A19,Bugs!$O$5:$O$303,"Duplicate")+COUNTIFS(Bugs!$J$5:$J$303,A19,Bugs!$O$5:$O$303,"Not a bug") -> 0 | H19: =COUNTIFS(Bugs!$J$5:$J$303,A19,Bugs!$O$5:$O$303,"Needs info") -> 0
A20: All | B20: =SUM(B16:B19) -> 0 | C20: =SUM(C16:C19) -> 0 | D20: =SUM(D16:D19) -> 0 | E20: =SUM(E16:E19) -> 0 | F20: =SUM(F16:F19) -> 0 | G20: =SUM(G16:G19) -> 0 | H20: =SUM(H16:H19) -> 0
A21: "Open" means not Closed and not Won't fix, Duplicate or Not a bug. The example row (row 4 of Bugs) is not counted.
A24: KPI (plan section 9) | B24: Target | C24: Now
A25: Cases with a result | B25: 1 | C25: =I12 -> 0
A26: Cases Not run | B26: 0.02 | C26: =IF(B12=0,0,G12/B12) -> 0
A27: Bugs reproduced without asking (never Needs info) | B27: 0.9 | C27: =IF(COUNTA(Bugs!$A$5:$A$303)=0,"",COUNTIF(Bugs!$T$5:$T$303,"No")/COUNTA(Bugs!$A$5:$A$303))
A28: Bugs not closed as Duplicate or Not a bug | B28: 0.9 | C28: =IF(COUNTA(Bugs!$A$5:$A$303)=0,"",1-(COUNTIF(Bugs!$O$5:$O$303,"Duplicate")+COUNTIF(Bugs!$O$5:$O$303,"Not a bug"))/COUNTA(Bugs!$A$5:$A$303))
A29: S1 bugs messaged within 1 hour | B29: 1 | C29: =IF(COUNTIF(Bugs!$J$5:$J$303,"S1")=0,"",COUNTIFS(Bugs!$J$5:$J$303,"S1",Bugs!$U$5:$U$303,"Yes")/COUNTIF(Bugs!$J$5:$J$303,"S1"))
A30: Fixed bugs retested within 1 working day | B30: 0.95 | C30: =IF(COUNT(Bugs!$V$5:$V$303)=0,"",COUNTIF(Bugs!$V$5:$V$303,"<=1")/COUNT(Bugs!$V$5:$V$303))
A31: Daily logs done by 17:30 | B31: 1 | C31: =IF(COUNTA('Daily log'!$Q$4:$Q$23)=0,"",COUNTIF('Daily log'!$Q$4:$Q$23,"Yes")/COUNTA('Daily log'!$Q$4:$Q$23))
A32: Exploring sessions logged (of 5) | B32: 5 | C32: =COUNT(Exploratory!$E$4:$E$13) -> 0
A33: Targets come from the QA test plan, section 9. Blank means nothing to measure yet.
A36: Results by planned day | B36: Date | C36: Planned | D36: With a result | E36: Pass | F36: Fail | G36: Blocked | H36: Not run | I36: % with a result
A37: Day 1 | B37: ='Daily log'!B4 -> 46328 | C37: ='Daily log'!C4 -> 8 | D37: ='Daily log'!D4 -> 0 | E37: ='Daily log'!E4 -> 0 | F37: ='Daily log'!F4 -> 0 | G37: ='Daily log'!G4 -> 0 | H37: ='Daily log'!H4 -> 0 | I37: =IF(C37=0,0,(E37+F37+G37)/C37) -> 0
A38: Day 2 | B38: ='Daily log'!B5 -> 46329 | C38: ='Daily log'!C5 -> 18 | D38: ='Daily log'!D5 -> 0 | E38: ='Daily log'!E5 -> 0 | F38: ='Daily log'!F5 -> 0 | G38: ='Daily log'!G5 -> 0 | H38: ='Daily log'!H5 -> 0 | I38: =IF(C38=0,0,(E38+F38+G38)/C38) -> 0
A39: Day 3 | B39: ='Daily log'!B6 -> 46330 | C39: ='Daily log'!C6 -> 17 | D39: ='Daily log'!D6 -> 0 | E39: ='Daily log'!E6 -> 0 | F39: ='Daily log'!F6 -> 0 | G39: ='Daily log'!G6 -> 0 | H39: ='Daily log'!H6 -> 0 | I39: =IF(C39=0,0,(E39+F39+G39)/C39) -> 0
A40: Day 4 | B40: ='Daily log'!B7 -> 46331 | C40: ='Daily log'!C7 -> 16 | D40: ='Daily log'!D7 -> 0 | E40: ='Daily log'!E7 -> 0 | F40: ='Daily log'!F7 -> 0 | G40: ='Daily log'!G7 -> 0 | H40: ='Daily log'!H7 -> 0 | I40: =IF(C40=0,0,(E40+F40+G40)/C40) -> 0
A41: Day 5 | B41: ='Daily log'!B8 -> 46332 | C41: ='Daily log'!C8 -> 19 | D41: ='Daily log'!D8 -> 0 | E41: ='Daily log'!E8 -> 0 | F41: ='Daily log'!F8 -> 0 | G41: ='Daily log'!G8 -> 0 | H41: ='Daily log'!H8 -> 0 | I41: =IF(C41=0,0,(E41+F41+G41)/C41) -> 0
A42: Day 6 | B42: ='Daily log'!B9 -> 46335 | C42: ='Daily log'!C9 -> 26 | D42: ='Daily log'!D9 -> 0 | E42: ='Daily log'!E9 -> 0 | F42: ='Daily log'!F9 -> 0 | G42: ='Daily log'!G9 -> 0 | H42: ='Daily log'!H9 -> 0 | I42: =IF(C42=0,0,(E42+F42+G42)/C42) -> 0
A43: Day 7 | B43: ='Daily log'!B10 -> 46336 | C43: ='Daily log'!C10 -> 26 | D43: ='Daily log'!D10 -> 0 | E43: ='Daily log'!E10 -> 0 | F43: ='Daily log'!F10 -> 0 | G43: ='Daily log'!G10 -> 0 | H43: ='Daily log'!H10 -> 0 | I43: =IF(C43=0,0,(E43+F43+G43)/C43) -> 0
A44: Day 8 | B44: ='Daily log'!B11 -> 46337 | C44: ='Daily log'!C11 -> 26 | D44: ='Daily log'!D11 -> 0 | E44: ='Daily log'!E11 -> 0 | F44: ='Daily log'!F11 -> 0 | G44: ='Daily log'!G11 -> 0 | H44: ='Daily log'!H11 -> 0 | I44: =IF(C44=0,0,(E44+F44+G44)/C44) -> 0
A45: Day 9 | B45: ='Daily log'!B12 -> 46338 | C45: ='Daily log'!C12 -> 21 | D45: ='Daily log'!D12 -> 0 | E45: ='Daily log'!E12 -> 0 | F45: ='Daily log'!F12 -> 0 | G45: ='Daily log'!G12 -> 0 | H45: ='Daily log'!H12 -> 0 | I45: =IF(C45=0,0,(E45+F45+G45)/C45) -> 0
A46: Day 10 | B46: ='Daily log'!B13 -> 46339 | C46: ='Daily log'!C13 -> 16 | D46: ='Daily log'!D13 -> 0 | E46: ='Daily log'!E13 -> 0 | F46: ='Daily log'!F13 -> 0 | G46: ='Daily log'!G13 -> 0 | H46: ='Daily log'!H13 -> 0 | I46: =IF(C46=0,0,(E46+F46+G46)/C46) -> 0
A47: Day 11 | B47: ='Daily log'!B14 -> 46342 | C47: ='Daily log'!C14 -> 19 | D47: ='Daily log'!D14 -> 0 | E47: ='Daily log'!E14 -> 0 | F47: ='Daily log'!F14 -> 0 | G47: ='Daily log'!G14 -> 0 | H47: ='Daily log'!H14 -> 0 | I47: =IF(C47=0,0,(E47+F47+G47)/C47) -> 0
A48: Day 12 | B48: ='Daily log'!B15 -> 46343 | C48: ='Daily log'!C15 -> 25 | D48: ='Daily log'!D15 -> 0 | E48: ='Daily log'!E15 -> 0 | F48: ='Daily log'!F15 -> 0 | G48: ='Daily log'!G15 -> 0 | H48: ='Daily log'!H15 -> 0 | I48: =IF(C48=0,0,(E48+F48+G48)/C48) -> 0
... A56: Day 20 | B56: ='Daily log'!B23 -> 46353 | C56: ='Daily log'!C23 -> 7 | D56: ='Daily log'!D23 -> 0 | E56: ='Daily log'!E23 -> 0 | F56: ='Daily log'!F23 -> 0 | G56: ='Daily log'!G23 -> 0 | H56: ='Daily log'!H23 -> 0 | I56: =IF(C56=0,0,(E56+F56+G56)/C56) -> 0

Sheet Test cases
A1: ID | B1: Area | C1: Feature | D1: What to do | E1: Expected result | F1: Needs | G1: Day | H1: Planned date | I1: Regression | J1: Result | K1: Date run | L1: Device and browser | M1: Bug IDs | N1: Notes
A2: SM-01 | B2: Smoke test | C2: Smoke | D2: Open the staging address on a laptop and on your phone | E2: The sign-in page loads on both, in Taskiem's look, with no error | G2: 1 | H2: 46328 | I2: R
A3: SM-02 | B3: Smoke test | C3: Smoke | D3: Sign in with the test owner account | E3: You land on the dashboard; your organisation's name shows | G3: 1 | H3: 46328 | I3: R
A4: SM-03 | B4: Smoke test | C4: Smoke | D4: Open every item in the menu once | E4: Each page opens; nothing is blank or shows a technical error | G4: 1 | H4: 46328
A5: SM-04 | B5: Smoke test | C5: Smoke | D5: Run the workflow "Remind me every day" from its template, once | E5: The run completes and the reminder arrives on Telegram | F5: Telegram | G5: 1 | H5: 46328 | I5: R
A6: SM-05 | B6: Smoke test | C6: Smoke | D6: Open the operator console (/ops) | E6: Storefront reviews, Reports and Field agents show | F6: Operator account | G6: 1 | H6: 46328
A7: SM-06 | B7: Smoke test | C7: Smoke | D7: Create a data table with one column and add one row | E7: The table and row are saved | G7: 1 | H7: 46328
A8: SM-07 | B8: Smoke test | C8: Smoke | D8: Send "help" to the Taskiem bot on Telegram | E8: The bot answers with what you can do, starting with your organisation's name in brackets | F8: Telegram | G8: 1 | H8: 46328 | I8: R
A9: SM-08 | B9: Smoke test | C9: Smoke | D9: Sign out, then try to open the dashboard address directly | E9: You are sent to the sign-in page | G9: 1 | H9: 46328
A10: CP-01 | B10: Core platform | C10: Sign-up | D10: On the sign-in page choose "Create an account"; fill in organisation, your name, a new email and a 12+ character password | E10: You are signed in at once and land on Get started | F10: Email | G10: 2 | H10: 46329 | I10: R
A11: CP-02 | B11: Core platform | C11: Sign-up | D11: Try to sign up with a password of 11 characters; then with the password equal to the email | E11: Both refused with a plain message | G11: 2 | H11: 46329
A12: CP-03 | B12: Core platform | C12: Sign-up | D12: Try to sign up with an email that already has an account | E12: Refused: the email is already in use | G12: 2 | H12: 46329
A13: CP-04 | B13: Core platform | C13: Sign-up | D13: Try a throwaway mailbox address (for example a mailinator.com address) and a name containing a web link | E13: Both refused | G13: 2 | H13: 46329
A14: CP-05 | B14: Core platform | C14: Sign-up | D14: Make 6 sign-ups from the same network in one day | E14: The sixth is refused (limit of 5 a day per address, unless engineering changed it) | G14: 2 | H14: 46329
A15: CP-06 | B15: Core platform | C15: Email confirmation | D15: Open the confirmation email and click the link | E15: Email confirmed; the checklist ticks "Confirm your email" | F15: Email | G15: 2 | H15: 46329 | I15: R
A16: CP-07 | B16: Core platform | C16: Email confirmation | D16: Click the same confirmation link a second time; then use a link older than 24 hours if you have one | E16: The used link does not work again; the old link is refused | F16: Email | G16: 2 | H16: 46329
A17: CP-08 | B17: Core platform | C17: Email confirmation | D17: Before confirming, try to invite a member and to create an API key | E17: Both refused with "confirm your email address first" | G17: 2 | H17: 46329
A18: CP-09 | B18: Core platform | C18: Email confirmation | D18: On Get started press "Send the link again" four times | E18: Three are sent; the fourth asks you to wait (one every 20 minutes) | F18: Email | G18: 2 | H18: 46329
A19: CP-10 | B19: Core platform | C19: Get started | D19: Work through the checklist: confirm email, link Telegram, pick a template, connect, publish, run once, invite a teammate | E19: Each step ticks itself when done; the page shows the minutes from sign-up to first successful run | G19: 2 | H19: 46329 | I19: R
A20: CP-11 | B20: Core platform | C20: Get started | D20: Time yourself from sign-up to the first successful run using the guided first workflow | E20: Under 15 minutes. Record the time and what slowed you down | G20: 2 | H20: 46329
A21: CP-12 | B21: Core platform | C21: Get started | D21: Open the help panels on Get started, Templates, Connections and Settings | E21: Each shows a few plain sentences; any "learn more" link opens a real page | G21: 2 | H21: 46329
A22: CP-13 | B22: Core platform | C22: Sign-in | D22: Sign in with a wrong password several times | E22: Refused each time with a plain message; after many tries you are slowed down | G22: 2 | H22: 46329
A23: CP-14 | B23: Core platform | C23: Password | D23: Change your password under Account; sign out and in with the new one | E23: Old password no longer works; new one does | G23: 2 | H23: 46329
A24: CP-15 | B24: Core platform | C24: Password | D24: Use "forgot password" (if offered) and follow the email link | E24: You can set a new password; the link works once | F24: Email | G24: 2 | H24: 46329
A25: CP-16 | B25: Core platform | C25: Passkey | D25: Under Account add a passkey (phone fingerprint or PIN); sign out; "Sign in with a passkey" | E25: Signed in without a password | F25: Phone | G25: 2 | H25: 46329
A26: CP-17 | B26: Core platform | C26: Authenticator | D26: Under Account set up an authenticator app (Google Authenticator or similar) and confirm a code | E26: Enrolled. Five wrong codes in a row lock codes for 15 minutes | F26: Phone | G26: 2 | H26: 46329
A27: CP-18 | B27: Core platform | C27: Sessions | D27: Sign in on laptop and phone; sign out on one | E27: The other session still works until signed out; signed-out pages are not reachable with Back | G27: 2 | H27: 46329
A28: CP-19 | B28: Core platform | C28: Members | D28: Members & keys: invite a second email as Operator; accept the invitation from that mailbox | E28: The person joins with the Operator role | F28: Email, second person | G28: 3 | H28: 46330
A29: CP-20 | B29: Core platform | C29: Members | D29: Invite someone, then cancel the invitation before it is accepted | E29: The link no longer works | G29: 3 | H29: 46330
A30: CP-21 | B30: Core platform | C30: Roles | D30: Signed in as a Viewer, try to edit a workflow, create a table and open Members | E30: Not allowed: buttons hidden or a plain refusal, never a crash | F30: Second person | G30: 3 | H30: 46330 | I30: R
A31: CP-22 | B31: Core platform | C31: Roles | D31: As a Viewer, paste the address of an owner-only page (for example /settings/billing or a workflow's edit page) into the browser | E31: Refused; no data shown | F31: Second person | G31: 3 | H31: 46330 | I31: R
A32: CP-23 | B32: Core platform | C32: Custom roles | D32: Create a custom role (for example Cashier) with two permissions; give it to a member | E32: The member can do exactly those two things and nothing else | G32: 3 | H32: 46330
A33: CP-24 | B33: Core platform | C33: Members | D33: Remove a member; the removed person tries to sign in to the organisation | E33: They no longer reach it | G33: 3 | H33: 46330
A34: CP-25 | B34: Core platform | C34: Audit log | D34: Open the audit log after the steps above | E34: Every invite, role change, removal and sign-in change is listed with who and when | G34: 3 | H34: 46330
A35: CP-26 | B35: Core platform | C35: Personal data | D35: Open a table with phone numbers as a member without the reveal permission; then as owner press Show | E35: Masked for the member (•••4567); shown for the owner, and the reveal appears in the audit log | G35: 3 | H35: 46330
A36: CP-27 | B36: Core platform | C36: Templates | D36: Open Templates; search for "reminder"; open three templates | E36: Search finds them; each template page says what it does and what it needs in plain words | G36: 3 | H36: 46330
A37: CP-28 | B37: Core platform | C37: Templates | D37: Set up "Remind me every day" through the guided screen; publish; run once | E37: Completes; the reminder arrives on Telegram | F37: Telegram | G37: 3 | H37: 46330 | I37: R
A38: CP-29 | B38: Core platform | C38: Templates | D38: Set up "Weekly SMS reminders from your debtors data table": let it make the debtors table; add two debtors with your own phone numbers; run it | E38: Each debtor with a balance gets an SMS; the run lists each one | F38: SMS | G38: 3 | H38: 46330
A39: CP-30 | B39: Core platform | C39: Templates | D39: Set up "Send an invoice and hear when it is paid" | E39: Invoice is sent; when paid with a Paystack test card the owner hears | F39: Paystack test, SMS or email | G39: 3 | H39: 46330
A40: CP-31 | B40: Core platform | C40: Templates | D40: Fill a template's details with mistakes: leave a required box empty, type letters in a time box | E40: Each mistake is pointed out in plain words before saving | G40: 3 | H40: 46330
A41: CP-32 | B41: Core platform | C41: Connections | D41: Connections: connect Paystack with the TEST secret key | E41: Accepted and checked; shown as test mode | F41: Paystack test | G41: 3 | H41: 46330 | I41: R
A42: CP-33 | B42: Core platform | C42: Connections | D42: Try to connect Paystack with a wrong key | E42: Refused with a plain message; nothing saved | G42: 3 | H42: 46330
A43: CP-34 | B43: Core platform | C43: Connections | D43: Switch a connection off; try to publish a workflow that uses it | E43: Publishing is refused, listing the connection as needed, with a Connect button | G43: 3 | H43: 46330 | I43: R
A44: CP-35 | B44: Core platform | C44: Readiness | D44: Publish a workflow that writes to a table that does not exist | E44: Refused; offered "Make it" with the right columns; after making it, publishing succeeds | G44: 3 | H44: 46330
A45: CP-36 | B45: Core platform | C45: Builder | D45: Workflows > New workflow; try each "When should it run?" card once | E45: Each opens the builder with the right first card | G45: 4 | H45: 46331
A46: CP-37 | B46: Core platform | C46: Builder | D46: Build: On a schedule > send yourself a Telegram message (Tell me). Use + to add the step. Test workflow | E46: Each step gets a green tick; nothing is actually sent during a test | G46: 4 | H46: 46331 | I46: R
A47: CP-38 | B47: Core platform | C47: Builder | D47: Add an If with a Yes and an empty No; test with values that take each path | E47: The path not taken is faded "Did not need to run" | G47: 4 | H47: 46331
A48: CP-39 | B48: Core platform | C48: Builder | D48: Add a value from an earlier step into a message using "/" or Add a field | E48: The value appears in the message when the workflow runs | G48: 4 | H48: 46331
A49: CP-40 | B49: Core platform | C49: Builder | D49: Move cards, Tidy up, Undo and Redo, add a note, delete a step | E49: Each works; deleting a step joins the steps around it | G49: 4 | H49: 46331
A50: CP-41 | B50: Core platform | C50: Builder | D50: Save draft; publish; Start run; open the Runs tab | E50: A new version is saved; the run appears with each step's result | G50: 4 | H50: 46331 | I50: R
A51: CP-42 | B51: Core platform | C51: Builder | D51: Open the same workflow in two browser tabs; change and save in both | E51: The second save merges or shows the conflict to choose; nothing is lost silently | G51: 4 | H51: 46331
A52: CP-43 | B52: Core platform | C52: Builder | D52: Open the builder on your phone | E52: Steps show as a list; a step's window opens full screen; Save draft and Publish work | F52: Phone | G52: 4 | H52: 46331
A53: CP-44 | B53: Core platform | C53: Builder | D53: Try to publish a workflow with no steps | E53: Refused with a plain message | G53: 4 | H53: 46331
A54: CP-45 | B54: Core platform | C54: Plain words | D54: Across the builder with Advanced OFF, look for technical words (JSON, schema, expression, cron, kobo, token, webhook, payload, API key) | E54: None appear outside Details or Advanced. Log each one found | G54: 4 | H54: 46331
A55: CP-46 | B55: Core platform | C55: Runs | D55: Make a run fail on purpose (for example a message to an invalid phone number); open the run | E55: The failed step is marked; the error is in plain words, technical detail under Details | G55: 4 | H55: 46331
A56: CP-47 | B56: Core platform | C56: Runs | D56: Use the run list filters (status, workflow); open a running run | E56: Filters work; the live view updates as steps finish | G56: 4 | H56: 46331
A57: CP-48 | B57: Core platform | C57: AI builder | D57: Describe it: "every Friday at 10am text the customers in my debtors table who still owe me" | E57: A draft is built, read back as plain numbered steps, and saved only after you confirm | F57: AI key on staging | G57: 4 | H57: 46331
A58: CP-49 | B58: Core platform | C58: AI builder | D58: Ask it for something that moves money ("pay my staff every month end") | E58: It drafts with an approval before any payment; it never publishes by itself | F58: AI key on staging | G58: 4 | H58: 46331
A59: CP-50 | B59: Core platform | C59: AI builder | D59: Ask for nonsense, or something Taskiem cannot do | E59: A polite answer, no broken draft | G59: 4 | H59: 46331
A60: CP-51 | B60: Core platform | C60: AI repair | D60: On a failed run, open the repair suggestion (if shown) | E60: It explains the fix in plain words; accepting needs a normal publish | F60: AI key on staging | G60: 4 | H60: 46331
A61: CP-52 | B61: Core platform | C61: Tables | D61: Tables > New table "debtors": name (text, required), phone (phone), balance (number), paid (yes/no) | E61: Created (the first table can take a minute or two) | G61: 5 | H61: 46332 | I61: R
A62: CP-53 | B62: Core platform | C62: Tables | D62: Add rows: a correct one; one with no name; one with letters in balance; one with a phone in local form 080… | E62: Bad rows refused with the reason; the phone is stored as +234… | G62: 5 | H62: 46332 | I62: R
A63: CP-54 | B63: Core platform | C63: Tables | D63: Import a CSV of 50 rows with 3 bad rows; export the table as CSV | E63: Good rows in, bad rows reported with their line; export opens in Excel correctly | F63: CSV file | G63: 5 | H63: 46332
A64: CP-55 | B64: Core platform | C64: Tables | D64: Add a column; drop a column; try to add a required column to a table that has rows | E64: Add and drop work (drop asks to confirm); the required column is refused | G64: 5 | H64: 46332
A65: CP-56 | B65: Core platform | C65: Tables | D65: Delete a table used by a published workflow | E65: You are warned or refused; nothing breaks silently | G65: 5 | H65: 46332
A66: CP-57 | B66: Core platform | C66: Approvals | D66: Workflow with an approval step for role Owner; start it; approve from the Approvals inbox | E66: The run waits, then continues after approval | G66: 5 | H66: 46332 | I66: R
A67: CP-58 | B67: Core platform | C67: Approvals | D67: Same, but reject | E67: The run takes the rejected path or stops, as designed | G67: 5 | H67: 46332
A68: CP-59 | B68: Core platform | C68: Approvals | D68: Approval needing two people (four-eyes); the person who started it tries to approve | E68: Self-approval refused; a second person can approve | F68: Second person | G68: 5 | H68: 46332 | I68: R
A69: CP-60 | B69: Core platform | C69: Approvals | D69: Approval policy with step-up (authenticator); approve | E69: Asks for the authenticator code or passkey before accepting | G69: 5 | H69: 46332
A70: CP-61 | B70: Core platform | C70: Approvals | D70: Delegate your approval role to a colleague for 2 days | E70: The colleague sees requests marked "covering for…"; ending the delegation stops it | F70: Second person | G70: 5 | H70: 46332
A71: CP-62 | B71: Core platform | C71: Approvals | D71: Leave an approval past its timeout | E71: It does what the step says on timeout (reject, fail or escalate) | G71: 5 | H71: 46332
A72: CP-63 | B72: Core platform | C72: Settings | D72: Secrets & settings: add a setting, a secret; use both in a workflow | E72: Workflow reads them; the secret is never shown again in full | G72: 5 | H72: 46332
A73: CP-64 | B73: Core platform | C73: Settings | D73: Turn the Advanced switch on and off | E73: Advanced shows step ids, Code and JSON tabs; off hides them | G73: 5 | H73: 46332
A74: CP-65 | B74: Core platform | C74: Alerts | D74: Settings > Alerts: a Telegram alert channel for failed runs; make a run fail | E74: The alert arrives on Telegram | F74: Telegram | G74: 5 | H74: 46332
A75: CP-66 | B75: Core platform | C75: People you message | D75: Settings > People you message: a customer opts in to Telegram updates via a form's thank-you page; then sends STOP | E75: Updates arrive on Telegram, not SMS; after STOP they stop; Remove removes the person | F75: Telegram, second Telegram account | G75: 5 | H75: 46332
A76: CP-67 | B76: Core platform | C76: Email trigger | D76: A workflow started by an email; send an email to its address | E76: A run starts with the email's details | F76: Mail domain on staging | G76: 5 | H76: 46332
A77: CP-68 | B77: Core platform | C77: Phone app | D77: On your phone, "Add to Home screen"; open Taskiem from the icon; approve something from Home | E77: Opens like an app; approving works | F77: Phone | G77: 5 | H77: 46332
A78: CP-69 | B78: Core platform | C78: Languages | D78: Switch the language (Pidgin, Yoruba, Hausa, Igbo) if offered | E78: Messages change language. Note they are drafts awaiting native-speaker review; log only broken screens, not wording | G78: 5 | H78: 46332
A79: CP-70 | B79: Core platform | C79: Billing | D79: Settings > Billing (only if engineering turns billing on for a test organisation): view the trial, choose a plan, pay with a Paystack test card | E79: Plan changes after payment; an invoice with VAT appears | F79: Paystack test, billing on | G79: 5 | H79: 46332
A80: CH-01 | B80: Chat (Telegram) | C80: Telegram linking | D80: Account > Telegram: Link Telegram; confirm it is you; open the link on your phone; press Start | E80: The bot says your account is linked | F80: Telegram | G80: 6 | H80: 46335 | I80: R
A81: CH-02 | B81: Chat (Telegram) | C81: Telegram linking | D81: Open the same link again; open a link older than 10 minutes | E81: Both refused | F81: Telegram | G81: 6 | H81: 46335
A82: CH-03 | B82: Chat (Telegram) | C82: Telegram linking | D82: Unlink in the web app; send "status" to the bot | E82: The bot no longer acts for you | F82: Telegram | G82: 6 | H82: 46335
A83: CH-04 | B83: Chat (Telegram) | C83: Chat | D83: Send help, status, "what failed today?" | E83: Correct answers for your organisation; personal data masked | F83: Telegram | G83: 6 | H83: 46335
A84: CH-05 | B84: Chat (Telegram) | C84: Chat | D84: Send "run <workflow name>"; answer each input; reply yes | E84: Nothing starts before yes; then the run starts and you hear how it ended | F84: Telegram | G84: 6 | H84: 46335 | I84: R
A85: CH-06 | B85: Chat (Telegram) | C85: Chat | D85: During "run", give a wrong value (letters for an amount); then send cancel | E85: The wrong value is explained and asked again; cancel drops it | F85: Telegram | G85: 6 | H85: 46335
A86: CH-07 | B86: Chat (Telegram) | C86: Chat | D86: Send "run" with a workflow name that does not exist, or one you may not start | E86: A polite answer; nothing starts | F86: Telegram | G86: 6 | H86: 46335
A87: CH-08 | B87: Chat (Telegram) | C87: Chat approvals | D87: Start a workflow with an approval; approve with the Approve button on Telegram | E87: The run continues; pressing the same button again does nothing | F87: Telegram | G87: 6 | H87: 46335 | I87: R
A88: CH-09 | B88: Chat (Telegram) | C88: Chat approvals | D88: An approval that needs step-up; tap Approve | E88: You get a link; it works signed in with passkey or code within 10 minutes; the decision is recorded | F88: Telegram | G88: 6 | H88: 46335
A89: CH-10 | B89: Chat (Telegram) | C89: Chat approvals | D89: Send "approvals" | E89: Waiting requests are sent again with fresh buttons (three at most) | F89: Telegram | G89: 6 | H89: 46335
A90: CH-11 | B90: Chat (Telegram) | C90: Chat tables | D90: Send tables; "add to debtors"; answer each column; yes | E90: The row is added with values checked; personal values masked in the reply | F90: Telegram | G90: 6 | H90: 46335 | I90: R
A91: CH-12 | B91: Chat (Telegram) | C91: Chat tables | D91: Send "find debtors Chidi" | E91: Up to five rows, masked, and how many more | F91: Telegram | G91: 6 | H91: 46335
A92: CH-13 | B92: Chat (Telegram) | C92: Chat build | D92: Send "build every Friday text my customers who owe me" | E92: Plain steps read back; draft saved only after yes; never published from chat | F92: Telegram, AI key | G92: 6 | H92: 46335
A93: CH-14 | B93: Chat (Telegram) | C93: Chat money | D93: Send "invoice Ada 25,000 for 5 bags of rice"; give a phone; yes | E93: Invoice shown with the number masked; sent by SMS after yes | F93: Telegram, SMS | G93: 6 | H93: 46335
A94: CH-15 | B94: Chat (Telegram) | C94: Chat money | D94: Send "spent 12k on diesel at Total" and "cash in 20,000 till" | E94: Each is recorded in the money log after yes | F94: Telegram | G94: 6 | H94: 46335
A95: CH-16 | B95: Chat (Telegram) | C95: Chat | D95: Belong to two organisations; send "switch"; then "switch <name>" | E95: Lists them; then works in the chosen one; every message starts with its name | F95: Telegram | G95: 6 | H95: 46335
A96: CH-17 | B96: Chat (Telegram) | C96: Chat | D96: Add the bot to a Telegram group and send "status" there | E96: The bot does not answer in groups | F96: Telegram | G96: 6 | H96: 46335
A97: CH-18 | B97: Chat (Telegram) | C97: Chat | D97: Send random text, a sticker, a very long message | E97: A polite answer; no crash; no technical words | F97: Telegram | G97: 6 | H97: 46335
A98: CH-19 | B98: Chat (Telegram) | C98: Chat | D98: Send a voice note (if voice notes are on) | E98: It is understood, or a polite "not available" | F98: Telegram | G98: 6 | H98: 46335
A99: CH-20 | B99: Chat (Telegram) | C99: Chat roles | D99: As a Viewer, send "run <workflow>" and "add to debtors" | E99: Refused politely, for lack of permission | F99: Telegram, second person | G99: 6 | H99: 46335
A100: RC-01 | B100: Reconciliation: invoices, payments and money | C100: Invoices | D100: Invoices > New invoice: customer name, phone and email, one amount with a description, due date and note. Save | E100: Saved as Draft with the next number (INV-0001 upwards); a draft can still be changed | | G100: 6 | H100: 46335 | I100: R
...

Sheet Bugs
A1: Bugs
A2: One row per bug. Row 4 is an example: delete it before your first weekly report.
A3: Bug ID | B3: Date found | C3: Time found | D3: Test case | E3: Area | F3: Title | G3: Steps to reproduce | H3: Expected | I3: Actual | J3: Severity | K3: Type | L3: Device and browser | M3: Account and organisation | N3: Evidence link | O3: Status | P3: Priority | Q3: Assigned to | R3: Fixed on | S3: Retest date | T3: Ever set to Needs info? | U3: S1 messaged within 1 hour? | V3: Working days to retest | W3: Notes
A4: BUG-000 (example) | B4: 46336 | C4: 10:42 | D4: RC-28 | E4: Reconciliation | F4: Part payment of ₦4,000 leaves the invoice showing "Awaiting payment" instead of "Part-paid" | G4: 1. QA Trading, Invoices > Settings: Customers may pay part ON. 2. New invoice ₦10,000 to Customer 1; Send. 3. On Customer 1's phone, pay ₦4,000 by card (Paystack test). 4. Wait 1 minute; refresh the invoice. | H4: Part-paid; paid ₦4,000; due ₦6,000 | I4: Stays "Awaiting payment"; paid ₦0. Paystack test shows the payment successful at 10:42 | J4: S1 | K4: Bug | L4: Tecno Spark 10, Chrome | M4: Customer 1; QA Trading | N4: (link to BUG-000-1.png) | O4: Fixed: ready to retest | P4: P1 | Q4: (engineer) | R4: 46337 | S4: 46338 | T4: No | U4: Yes | V4: =IF(AND(R4<>"",S4<>""),NETWORKDAYS(R4,S4)-1,"") -> 1 | W4: Invented example to show the format
V5: =IF(AND(R5<>"",S5<>""),NETWORKDAYS(R5,S5)-1,"")
V6: =IF(AND(R6<>"",S6<>""),NETWORKDAYS(R6,S6)-1,"")
V7: =IF(AND(R7<>"",S7<>""),NETWORKDAYS(R7,S7)-1,"")
V8: =IF(AND(R8<>"",S8<>""),NETWORKDAYS(R8,S8)-1,"")
V9: =IF(AND(R9<>"",S9<>""),NETWORKDAYS(R9,S9)-1,"")
V10: =IF(AND(R10<>"",S10<>""),NETWORKDAYS(R10,S10)-1,"")
V11: =IF(AND(R11<>"",S11<>""),NETWORKDAYS(R11,S11)-1,"")
V12: =IF(AND(R12<>"",S12<>""),NETWORKDAYS(R12,S12)-1,"")
V13: =IF(AND(R13<>"",S13<>""),NETWORKDAYS(R13,S13)-1,"")
V14: =IF(AND(R14<>"",S14<>""),NETWORKDAYS(R14,S14)-1,"")
V15: =IF(AND(R15<>"",S15<>""),NETWORKDAYS(R15,S15)-1,"")
V16: =IF(AND(R16<>"",S16<>""),NETWORKDAYS(R16,S16)-1,"")
... V303: =IF(AND(R303<>"",S303<>""),NETWORKDAYS(R303,S303)-1,"")

Sheet Daily log
A1: Daily log
A2: Fill in by 17:30 each day. The grey-headed count columns fill themselves from the Test cases tab (by planned day).
A3: Day | B3: Date | C3: Planned cases | D3: With a result | E3: Pass | F3: Fail | G3: Blocked | H3: Not run | I3: Bugs logged today | J3: S1 and S2 bug IDs | K3: Retested | L3: Closed | M3: Reopened | N3: Blockers, and who you told | O3: Staging updates seen | P3: Notes | Q3: Done by 17:30?
A4: 1 | B4: 46328 | C4: =COUNTIF('Test cases'!$G$2:$G$380,A4) -> 8 | D4: =COUNTIFS('Test cases'!$G$2:$G$380,A4,'Test cases'!$J$2:$J$380,"<>") -> 0 | E4: =COUNTIFS('Test cases'!$G$2:$G$380,A4,'Test cases'!$J$2:$J$380,"Pass")+COUNTIFS('Test cases'!$G$2:$G$380,A4,'Test cases'!$J$2:$J$380,"Pass with note") -> 0 | F4: =COUNTIFS('Test cases'!$G$2:$G$380,A4,'Test cases'!$J$2:$J$380,"Fail") -> 0 | G4: =COUNTIFS('Test cases'!$G$2:$G$380,A4,'Test cases'!$J$2:$J$380,"Blocked") -> 0 | H4: =COUNTIFS('Test cases'!$G$2:$G$380,A4,'Test cases'!$J$2:$J$380,"Not run") -> 0 | I4: =COUNTIF(Bugs!$B$5:$B$303,B4) -> 0
A5: 2 | B5: 46329 | C5: =COUNTIF('Test cases'!$G$2:$G$380,A5) -> 18 | D5: =COUNTIFS('Test cases'!$G$2:$G$380,A5,'Test cases'!$J$2:$J$380,"<>") -> 0 | E5: =COUNTIFS('Test cases'!$G$2:$G$380,A5,'Test cases'!$J$2:$J$380,"Pass")+COUNTIFS('Test cases'!$G$2:$G$380,A5,'Test cases'!$J$2:$J$380,"Pass with note") -> 0 | F5: =COUNTIFS('Test cases'!$G$2:$G$380,A5,'Test cases'!$J$2:$J$380,"Fail") -> 0 | G5: =COUNTIFS('Test cases'!$G$2:$G$380,A5,'Test cases'!$J$2:$J$380,"Blocked") -> 0 | H5: =COUNTIFS('Test cases'!$G$2:$G$380,A5,'Test cases'!$J$2:$J$380,"Not run") -> 0 | I5: =COUNTIF(Bugs!$B$5:$B$303,B5) -> 0
A6: 3 | B6: 46330 | C6: =COUNTIF('Test cases'!$G$2:$G$380,A6) -> 17 | D6: =COUNTIFS('Test cases'!$G$2:$G$380,A6,'Test cases'!$J$2:$J$380,"<>") -> 0 | E6: =COUNTIFS('Test cases'!$G$2:$G$380,A6,'Test cases'!$J$2:$J$380,"Pass")+COUNTIFS('Test cases'!$G$2:$G$380,A6,'Test cases'!$J$2:$J$380,"Pass with note") -> 0 | F6: =COUNTIFS('Test cases'!$G$2:$G$380,A6,'Test cases'!$J$2:$J$380,"Fail") -> 0 | G6: =COUNTIFS('Test cases'!$G$2:$G$380,A6,'Test cases'!$J$2:$J$380,"Blocked") -> 0 | H6: =COUNTIFS('Test cases'!$G$2:$G$380,A6,'Test cases'!$J$2:$J$380,"Not run") -> 0 | I6: =COUNTIF(Bugs!$B$5:$B$303,B6) -> 0
A7: 4 | B7: 46331 | C7: =COUNTIF('Test cases'!$G$2:$G$380,A7) -> 16 | D7: =COUNTIFS('Test cases'!$G$2:$G$380,A7,'Test cases'!$J$2:$J$380,"<>") -> 0 | E7: =COUNTIFS('Test cases'!$G$2:$G$380,A7,'Test cases'!$J$2:$J$380,"Pass")+COUNTIFS('Test cases'!$G$2:$G$380,A7,'Test cases'!$J$2:$J$380,"Pass with note") -> 0 | F7: =COUNTIFS('Test cases'!$G$2:$G$380,A7,'Test cases'!$J$2:$J$380,"Fail") -> 0 | G7: =COUNTIFS('Test cases'!$G$2:$G$380,A7,'Test cases'!$J$2:$J$380,"Blocked") -> 0 | H7: =COUNTIFS('Test cases'!$G$2:$G$380,A7,'Test cases'!$J$2:$J$380,"Not run") -> 0 | I7: =COUNTIF(Bugs!$B$5:$B$303,B7) -> 0
A8: 5 | B8: 46332 | C8: =COUNTIF('Test cases'!$G$2:$G$380,A8) -> 19 | D8: =COUNTIFS('Test cases'!$G$2:$G$380,A8,'Test cases'!$J$2:$J$380,"<>") -> 0 | E8: =COUNTIFS('Test cases'!$G$2:$G$380,A8,'Test cases'!$J$2:$J$380,"Pass")+COUNTIFS('Test cases'!$G$2:$G$380,A8,'Test cases'!$J$2:$J$380,"Pass with note") -> 0 | F8: =COUNTIFS('Test cases'!$G$2:$G$380,A8,'Test cases'!$J$2:$J$380,"Fail") -> 0 | G8: =COUNTIFS('Test cases'!$G$2:$G$380,A8,'Test cases'!$J$2:$J$380,"Blocked") -> 0 | H8: =COUNTIFS('Test cases'!$G$2:$G$380,A8,'Test cases'!$J$2:$J$380,"Not run") -> 0 | I8: =COUNTIF(Bugs!$B$5:$B$303,B8) -> 0
A9: 6 | B9: 46335 | C9: =COUNTIF('Test cases'!$G$2:$G$380,A9) -> 26 | D9: =COUNTIFS('Test cases'!$G$2:$G$380,A9,'Test cases'!$J$2:$J$380,"<>") -> 0 | E9: =COUNTIFS('Test cases'!$G$2:$G$380,A9,'Test cases'!$J$2:$J$380,"Pass")+COUNTIFS('Test cases'!$G$2:$G$380,A9,'Test cases'!$J$2:$J$380,"Pass with note") -> 0 | F9: =COUNTIFS('Test cases'!$G$2:$G$380,A9,'Test cases'!$J$2:$J$380,"Fail") -> 0 | G9: =COUNTIFS('Test cases'!$G$2:$G$380,A9,'Test cases'!$J$2:$J$380,"Blocked") -> 0 | H9: =COUNTIFS('Test cases'!$G$2:$G$380,A9,'Test cases'!$J$2:$J$380,"Not run") -> 0 | I9: =COUNTIF(Bugs!$B$5:$B$303,B9) -> 0
A10: 7 | B10: 46336 | C10: =COUNTIF('Test cases'!$G$2:$G$380,A10) -> 26 | D10: =COUNTIFS('Test cases'!$G$2:$G$380,A10,'Test cases'!$J$2:$J$380,"<>") -> 0 | E10: =COUNTIFS('Test cases'!$G$2:$G$380,A10,'Test cases'!$J$2:$J$380,"Pass")+COUNTIFS('Test cases'!$G$2:$G$380,A10,'Test cases'!$J$2:$J$380,"Pass with note") -> 0 | F10: =COUNTIFS('Test cases'!$G$2:$G$380,A10,'Test cases'!$J$2:$J$380,"Fail") -> 0 | G10: =COUNTIFS('Test cases'!$G$2:$G$380,A10,'Test cases'!$J$2:$J$380,"Blocked") -> 0 | H10: =COUNTIFS('Test cases'!$G$2:$G$380,A10,'Test cases'!$J$2:$J$380,"Not run") -> 0 | I10: =COUNTIF(Bugs!$B$5:$B$303,B10) -> 0
A11: 8 | B11: 46337 | C11: =COUNTIF('Test cases'!$G$2:$G$380,A11) -> 26 | D11: =COUNTIFS('Test cases'!$G$2:$G$380,A11,'Test cases'!$J$2:$J$380,"<>") -> 0 | E11: =COUNTIFS('Test cases'!$G$2:$G$380,A11,'Test cases'!$J$2:$J$380,"Pass")+COUNTIFS('Test cases'!$G$2:$G$380,A11,'Test cases'!$J$2:$J$380,"Pass with note") -> 0 | F11: =COUNTIFS('Test cases'!$G$2:$G$380,A11,'Test cases'!$J$2:$J$380,"Fail") -> 0 | G11: =COUNTIFS('Test cases'!$G$2:$G$380,A11,'Test cases'!$J$2:$J$380,"Blocked") -> 0 | H11: =COUNTIFS('Test cases'!$G$2:$G$380,A11,'Test cases'!$J$2:$J$380,"Not run") -> 0 | I11: =COUNTIF(Bugs!$B$5:$B$303,B11) -> 0
A12: 9 | B12: 46338 | C12: =COUNTIF('Test cases'!$G$2:$G$380,A12) -> 21 | D12: =COUNTIFS('Test cases'!$G$2:$G$380,A12,'Test cases'!$J$2:$J$380,"<>") -> 0 | E12: =COUNTIFS('Test cases'!$G$2:$G$380,A12,'Test cases'!$J$2:$J$380,"Pass")+COUNTIFS('Test cases'!$G$2:$G$380,A12,'Test cases'!$J$2:$J$380,"Pass with note") -> 0 | F12: =COUNTIFS('Test cases'!$G$2:$G$380,A12,'Test cases'!$J$2:$J$380,"Fail") -> 0 | G12: =COUNTIFS('Test cases'!$G$2:$G$380,A12,'Test cases'!$J$2:$J$380,"Blocked") -> 0 | H12: =COUNTIFS('Test cases'!$G$2:$G$380,A12,'Test cases'!$J$2:$J$380,"Not run") -> 0 | I12: =COUNTIF(Bugs!$B$5:$B$303,B12) -> 0
A13: 10 | B13: 46339 | C13: =COUNTIF('Test cases'!$G$2:$G$380,A13) -> 16 | D13: =COUNTIFS('Test cases'!$G$2:$G$380,A13,'Test cases'!$J$2:$J$380,"<>") -> 0 | E13: =COUNTIFS('Test cases'!$G$2:$G$380,A13,'Test cases'!$J$2:$J$380,"Pass")+COUNTIFS('Test cases'!$G$2:$G$380,A13,'Test cases'!$J$2:$J$380,"Pass with note") -> 0 | F13: =COUNTIFS('Test cases'!$G$2:$G$380,A13,'Test cases'!$J$2:$J$380,"Fail") -> 0 | G13: =COUNTIFS('Test cases'!$G$2:$G$380,A13,'Test cases'!$J$2:$J$380,"Blocked") -> 0 | H13: =COUNTIFS('Test cases'!$G$2:$G$380,A13,'Test cases'!$J$2:$J$380,"Not run") -> 0 | I13: =COUNTIF(Bugs!$B$5:$B$303,B13) -> 0
A14: 11 | B14: 46342 | C14: =COUNTIF('Test cases'!$G$2:$G$380,A14) -> 19 | D14: =COUNTIFS('Test cases'!$G$2:$G$380,A14,'Test cases'!$J$2:$J$380,"<>") -> 0 | E14: =COUNTIFS('Test cases'!$G$2:$G$380,A14,'Test cases'!$J$2:$J$380,"Pass")+COUNTIFS('Test cases'!$G$2:$G$380,A14,'Test cases'!$J$2:$J$380,"Pass with note") -> 0 | F14: =COUNTIFS('Test cases'!$G$2:$G$380,A14,'Test cases'!$J$2:$J$380,"Fail") -> 0 | G14: =COUNTIFS('Test cases'!$G$2:$G$380,A14,'Test cases'!$J$2:$J$380,"Blocked") -> 0 | H14: =COUNTIFS('Test cases'!$G$2:$G$380,A14,'Test cases'!$J$2:$J$380,"Not run") -> 0 | I14: =COUNTIF(Bugs!$B$5:$B$303,B14) -> 0
A15: 12 | B15: 46343 | C15: =COUNTIF('Test cases'!$G$2:$G$380,A15) -> 25 | D15: =COUNTIFS('Test cases'!$G$2:$G$380,A15,'Test cases'!$J$2:$J$380,"<>") -> 0 | E15: =COUNTIFS('Test cases'!$G$2:$G$380,A15,'Test cases'!$J$2:$J$380,"Pass")+COUNTIFS('Test cases'!$G$2:$G$380,A15,'Test cases'!$J$2:$J$380,"Pass with note") -> 0 | F15: =COUNTIFS('Test cases'!$G$2:$G$380,A15,'Test cases'!$J$2:$J$380,"Fail") -> 0 | G15: =COUNTIFS('Test cases'!$G$2:$G$380,A15,'Test cases'!$J$2:$J$380,"Blocked") -> 0 | H15: =COUNTIFS('Test cases'!$G$2:$G$380,A15,'Test cases'!$J$2:$J$380,"Not run") -> 0 | I15: =COUNTIF(Bugs!$B$5:$B$303,B15) -> 0
... A23: 20 | B23: 46353 | C23: =COUNTIF('Test cases'!$G$2:$G$380,A23) -> 7 | D23: =COUNTIFS('Test cases'!$G$2:$G$380,A23,'Test cases'!$J$2:$J$380,"<>") -> 0 | E23: =COUNTIFS('Test cases'!$G$2:$G$380,A23,'Test cases'!$J$2:$J$380,"Pass")+COUNTIFS('Test cases'!$G$2:$G$380,A23,'Test cases'!$J$2:$J$380,"Pass with note") -> 0 | F23: =COUNTIFS('Test cases'!$G$2:$G$380,A23,'Test cases'!$J$2:$J$380,"Fail") -> 0 | G23: =COUNTIFS('Test cases'!$G$2:$G$380,A23,'Test cases'!$J$2:$J$380,"Blocked") -> 0 | H23: =COUNTIFS('Test cases'!$G$2:$G$380,A23,'Test cases'!$J$2:$J$380,"Not run") -> 0 | I23: =COUNTIF(Bugs!$B$5:$B$303,B23) -> 0

Sheet Exploratory
A1: Exploratory sessions
A2: One row per session. Charters are from the plan, section 4.3.
A3: Session | B3: Day | C3: Date | D3: Charter | E3: Minutes spent | F3: What I tried | G3: Bugs found (IDs) | H3: Questions and ideas
A4: 1 | B4: 5 | C4: 46332 | D4: Explore the workflow builder as a shop owner who has never used software like it, on a phone, to find where they would get stuck or lost
A5: 2 | B5: 10 | C5: 46339 | D5: Explore reconciliation with a messy month of money (a bank statement with odd references, part payments, a refund) to find wrong totals, lost payments or double counting
A6: 3 | B6: 15 | C6: 46346 | D6: Explore the storefront as a customer on a cheap phone and a slow network who orders, pays, changes their mind and books, to find anything that confuses or fails them
A7: 4 | B7: 19 | C7: 46352 | D7: Explore resumption morning at a school: parents paying cash, the gate checking children, the proprietor reading the close, to find delays, wrong clearance or confusing screens
A8: 5 | B8: 20 | C8: 46353 | D8: Free session: go back to the area with the most bugs and dig deeper

Sheet Accounts
A1: Test identities and organisations
A2: Never write a password here.
A3: Who | B3: Role in Taskiem | C3: Email | D3: Phone (last 4 digits) | E3: Organisations | F3: Telegram linked? | G3: Notes
A4: Owner A (you) | B4: Owner
A5: Owner B | B5: Owner
A6: Admin | B6: Admin
A7: Operator | B7: Operator
A8: Viewer or Auditor | B8: Viewer
A9: Bursar | B9: Bursar (custom role)
A10: Gate | B10: Gate
A11: Customer 1 | B11: No account
A12: Customer 2 | B12: No account
A13: Customer 3 | B13: No account
A14: Field agent | B14: Registered agent
A15: Platform operator | B15: Operator console
A17: Organisations
A18: Organisation | B18: Used for | C18: Owner | D18: Created on | E18: Notes
A19: QA Trading | B19: Core, chat, reconciliation
A20: QA Shop | B20: Storefront (one-person business)
A21: QA Shop Two | B21: Chat set-up, agent sign-up
A22: QA School | B22: Schools
A23: QA School Two | B23: Promotion
A24: QA Other | B24: Isolation checks (XC-10)

Sheet Lists
A1: Pass | B1: S1 | C1: New | D1: Bug | E1: Core | F1: P1 | G1: Yes
A2: Pass with note | B2: S2 | C2: Confirmed | D2: Wording | E2: Chat | F2: P2 | G2: No
A3: Fail | B3: S3 | C3: Needs info | D3: Design or usability | E3: Reconciliation | F3: P3
A4: Blocked | B4: S4 | C4: In progress | D4: Doc mismatch | E4: Storefront
A5: Not run | C5: Fixed: ready to retest | D5: Suggestion | E5: Schools
C6: Closed | E6: Across
C7: Reopened
C8: Won't fix
C9: Duplicate
C10: Not a bug
